[
  {
    "name": "רש\"י",
    "hebrew_date": {
      "month": 5,
      "day": 29
    },
    "notes": "רבי שלמה יצחקי"
  },
  {
    "name": "האר\"י הקדוש",
    "hebrew_date": {
      "month": 5,
      "day": 5
    },
    "notes": "רבי יצחק לוריא"
  },
  {
    "name": "הבעל שם טוב",
    "hebrew_date": {
      "month": 6,
      "day": 1
    },
    "notes": "רבי ישראל בן אליעזר"
  },
  {
    "name": "החפץ חיים",
    "hebrew_date": {
      "month": 6,
      "day": 24
    },
    "notes": "רבי ישראל מאיר הכהן"
  }
]